Metadata-Version: 2.1
Name: plagiarism-MCA2022temp
Version: 0.1
Summary: A Simple Plagiarism Checker
Home-page: https://github.com/mnk-q/plagy
Author: Piyush Devda
Author-email: piyushdevda03@gmail.com
License: UNKNOWN
Project-URL: Bug Tracker, https://github.com/mnk-q/plagy/issues
Platform: UNKNOWN
Classifier: Programming Language :: Python :: 3
Classifier: License :: OSI Approved :: MIT License
Classifier: Operating System :: OS Independent
Requires-Python: >=3.6
